[
  {
    "repo": "openclaw/openclaw",
    "run_id": "24937679258",
    "run_url": "https://github.com/openclaw/projectclownfish/actions/runs/24937679258",
    "cluster_id": "ghcrawl-143799-autonomous-smoke",
    "published_at": "2026-04-26T01:36:05.594Z",
    "target": "#65285",
    "action": "close_duplicate",
    "status": "executed",
    "classification": "duplicate",
    "canonical": "#61741",
    "candidate_fix": null,
    "title": null,
    "idempotency_key": "ghcrawl-143799-autonomous-smoke:#65285:close_duplicate:#61741:2026-04-12T16:11:09Z",
    "reason": "duplicate of the canonical thread",
    "merged_at": null,
    "merge_commit_sha": null,
    "live_state": "closed",
    "live_updated_at": "2026-04-12T16:11:09Z"
  },
  {
    "repo": "openclaw/openclaw",
    "run_id": "24937679258",
    "run_url": "https://github.com/openclaw/projectclownfish/actions/runs/24937679258",
    "cluster_id": "ghcrawl-143799-autonomous-smoke",
    "published_at": "2026-04-26T01:36:05.594Z",
    "target": "#69920",
    "action": "close_duplicate",
    "status": "executed",
    "classification": "duplicate",
    "canonical": "#61741",
    "candidate_fix": null,
    "title": null,
    "idempotency_key": "ghcrawl-143799-autonomous-smoke:#69920:close_duplicate:#61741:2026-04-22T01:29:17Z",
    "reason": "duplicate of the canonical thread",
    "merged_at": null,
    "merge_commit_sha": null,
    "live_state": "closed",
    "live_updated_at": "2026-04-22T01:29:17Z"
  },
  {
    "repo": "openclaw/openclaw",
    "run_id": "24939000666",
    "run_url": "https://github.com/openclaw/projectclownfish/actions/runs/24939000666",
    "cluster_id": "ghcrawl-143804-autonomous-smoke",
    "published_at": "2026-04-26T01:36:05.616Z",
    "target": "#70373",
    "action": "close_duplicate",
    "status": "executed",
    "classification": "duplicate",
    "canonical": "#68508",
    "candidate_fix": null,
    "title": null,
    "idempotency_key": "ghcrawl-143804-autonomous-smoke:#70373:close_duplicate:#68508:2026-04-22T22:52:51Z",
    "reason": "duplicate of the canonical thread",
    "merged_at": null,
    "merge_commit_sha": null,
    "live_state": "closed",
    "live_updated_at": "2026-04-22T22:52:51Z"
  },
  {
    "repo": "openclaw/openclaw",
    "run_id": "24939001644",
    "run_url": "https://github.com/openclaw/projectclownfish/actions/runs/24939001644",
    "cluster_id": "ghcrawl-143805-autonomous-smoke",
    "published_at": "2026-04-26T01:36:05.618Z",
    "target": "#65153",
    "action": "close_duplicate",
    "status": "executed",
    "classification": "duplicate",
    "canonical": "#62560",
    "candidate_fix": null,
    "title": null,
    "idempotency_key": "ghcrawl-143805-autonomous-smoke:#65153:close_duplicate:#62560:2026-04-12T04:34:31Z",
    "reason": "duplicate of the canonical thread",
    "merged_at": null,
    "merge_commit_sha": null,
    "live_state": "closed",
    "live_updated_at": "2026-04-12T04:34:31Z"
  },
  {
    "repo": "openclaw/openclaw",
    "run_id": "24939007967",
    "run_url": "https://github.com/openclaw/projectclownfish/actions/runs/24939007967",
    "cluster_id": "ghcrawl-143814-autonomous-smoke",
    "published_at": "2026-04-26T01:36:05.637Z",
    "target": "#64750",
    "action": "close_duplicate",
    "status": "executed",
    "classification": "duplicate",
    "canonical": "#63816",
    "candidate_fix": null,
    "title": null,
    "idempotency_key": "ghcrawl-143814-autonomous-smoke|#64750|close_duplicate|#63816|2026-04-11T10:25:09Z",
    "reason": "duplicate of the canonical thread",
    "merged_at": null,
    "merge_commit_sha": null,
    "live_state": "closed",
    "live_updated_at": "2026-04-11T10:25:09Z"
  },
  {
    "repo": "openclaw/openclaw",
    "run_id": "24939008778",
    "run_url": "https://github.com/openclaw/projectclownfish/actions/runs/24939008778",
    "cluster_id": "ghcrawl-143815-autonomous-smoke",
    "published_at": "2026-04-26T01:36:05.638Z",
    "target": "#50541",
    "action": "close_duplicate",
    "status": "executed",
    "classification": "duplicate",
    "canonical": "#49180",
    "candidate_fix": null,
    "title": null,
    "idempotency_key": "ghcrawl-143815-autonomous-smoke:#50541:close_duplicate:#49180:2026-03-30T21:20:25Z",
    "reason": "duplicate of the canonical thread",
    "merged_at": null,
    "merge_commit_sha": null,
    "live_state": "closed",
    "live_updated_at": "2026-03-30T21:20:25Z"
  },
  {
    "repo": "openclaw/openclaw",
    "run_id": "24939008778",
    "run_url": "https://github.com/openclaw/projectclownfish/actions/runs/24939008778",
    "cluster_id": "ghcrawl-143815-autonomous-smoke",
    "published_at": "2026-04-26T01:36:05.638Z",
    "target": "#50691",
    "action": "close_duplicate",
    "status": "executed",
    "classification": "duplicate",
    "canonical": "#49180",
    "candidate_fix": null,
    "title": null,
    "idempotency_key": "ghcrawl-143815-autonomous-smoke:#50691:close_duplicate:#49180:2026-03-30T21:20:53Z",
    "reason": "duplicate of the canonical thread",
    "merged_at": null,
    "merge_commit_sha": null,
    "live_state": "closed",
    "live_updated_at": "2026-03-30T21:20:53Z"
  },
  {
    "repo": "openclaw/openclaw",
    "run_id": "24939009401",
    "run_url": "https://github.com/openclaw/projectclownfish/actions/runs/24939009401",
    "cluster_id": "ghcrawl-143816-autonomous-smoke",
    "published_at": "2026-04-26T01:36:05.641Z",
    "target": "#70180",
    "action": "close_duplicate",
    "status": "executed",
    "classification": "duplicate",
    "canonical": "#33185",
    "candidate_fix": null,
    "title": null,
    "idempotency_key": "ghcrawl-143816-autonomous-smoke:#70180:close_duplicate:#33185:2026-04-25T07:25:46Z",
    "reason": "duplicate of the canonical thread",
    "merged_at": null,
    "merge_commit_sha": null,
    "live_state": "closed",
    "live_updated_at": "2026-04-25T07:25:46Z"
  },
  {
    "repo": "openclaw/openclaw",
    "run_id": "24939009401",
    "run_url": "https://github.com/openclaw/projectclownfish/actions/runs/24939009401",
    "cluster_id": "ghcrawl-143816-autonomous-smoke",
    "published_at": "2026-04-26T01:36:05.641Z",
    "target": "#65832",
    "action": "close_duplicate",
    "status": "executed",
    "classification": "duplicate",
    "canonical": "#33185",
    "candidate_fix": null,
    "title": null,
    "idempotency_key": "ghcrawl-143816-autonomous-smoke:#65832:close_duplicate:#33185:2026-04-13T09:15:11Z",
    "reason": "duplicate of the canonical thread",
    "merged_at": null,
    "merge_commit_sha": null,
    "live_state": "closed",
    "live_updated_at": "2026-04-13T09:15:11Z"
  },
  {
    "repo": "openclaw/openclaw",
    "run_id": "24939009401",
    "run_url": "https://github.com/openclaw/projectclownfish/actions/runs/24939009401",
    "cluster_id": "ghcrawl-143816-autonomous-smoke",
    "published_at": "2026-04-26T01:36:05.641Z",
    "target": "#66758",
    "action": "close_duplicate",
    "status": "executed",
    "classification": "duplicate",
    "canonical": "#33185",
    "candidate_fix": null,
    "title": null,
    "idempotency_key": "ghcrawl-143816-autonomous-smoke:#66758:close_duplicate:#33185:2026-04-14T19:25:32Z",
    "reason": "duplicate of the canonical thread",
    "merged_at": null,
    "merge_commit_sha": null,
    "live_state": "closed",
    "live_updated_at": "2026-04-14T19:25:32Z"
  },
  {
    "repo": "openclaw/openclaw",
    "run_id": "24939009401",
    "run_url": "https://github.com/openclaw/projectclownfish/actions/runs/24939009401",
    "cluster_id": "ghcrawl-143816-autonomous-smoke",
    "published_at": "2026-04-26T01:36:05.641Z",
    "target": "#67406",
    "action": "close_duplicate",
    "status": "executed",
    "classification": "duplicate",
    "canonical": "#33185",
    "candidate_fix": null,
    "title": null,
    "idempotency_key": "ghcrawl-143816-autonomous-smoke:#67406:close_duplicate:#33185:2026-04-22T17:36:07Z",
    "reason": "duplicate of the canonical thread",
    "merged_at": null,
    "merge_commit_sha": null,
    "live_state": "closed",
    "live_updated_at": "2026-04-22T17:36:07Z"
  },
  {
    "repo": "openclaw/openclaw",
    "run_id": "24939010877",
    "run_url": "https://github.com/openclaw/projectclownfish/actions/runs/24939010877",
    "cluster_id": "ghcrawl-143818-autonomous-smoke",
    "published_at": "2026-04-26T01:36:05.648Z",
    "target": "#54475",
    "action": "close_superseded",
    "status": "blocked",
    "classification": "superseded",
    "canonical": null,
    "candidate_fix": "#54774",
    "title": null,
    "idempotency_key": "ghcrawl-143818-autonomous-smoke:#54475:close_superseded:#54774:2026-03-25T16:21:44Z",
    "reason": "closure requires canonical or duplicate_of",
    "merged_at": null,
    "merge_commit_sha": null,
    "live_state": null,
    "live_updated_at": null
  },
  {
    "repo": "openclaw/openclaw",
    "run_id": "24939011554",
    "run_url": "https://github.com/openclaw/projectclownfish/actions/runs/24939011554",
    "cluster_id": "ghcrawl-143819-autonomous-smoke",
    "published_at": "2026-04-26T01:36:05.650Z",
    "target": "#67029",
    "action": "close_duplicate",
    "status": "executed",
    "classification": "duplicate",
    "canonical": "#68252",
    "candidate_fix": null,
    "title": null,
    "idempotency_key": "ghcrawl-143819-autonomous-smoke:issue-67029:close_duplicate:canon-68252:2026-04-23T11:56:51Z",
    "reason": "duplicate of the canonical thread",
    "merged_at": null,
    "merge_commit_sha": null,
    "live_state": "closed",
    "live_updated_at": "2026-04-23T11:56:51Z"
  },
  {
    "repo": "openclaw/openclaw",
    "run_id": "24939011554",
    "run_url": "https://github.com/openclaw/projectclownfish/actions/runs/24939011554",
    "cluster_id": "ghcrawl-143819-autonomous-smoke",
    "published_at": "2026-04-26T01:36:05.650Z",
    "target": "#69886",
    "action": "close_duplicate",
    "status": "executed",
    "classification": "duplicate",
    "canonical": "#68252",
    "candidate_fix": null,
    "title": null,
    "idempotency_key": "ghcrawl-143819-autonomous-smoke:issue-69886:close_duplicate:canon-68252:2026-04-22T00:15:15Z",
    "reason": "duplicate of the canonical thread",
    "merged_at": null,
    "merge_commit_sha": null,
    "live_state": "closed",
    "live_updated_at": "2026-04-22T00:15:15Z"
  },
  {
    "repo": "openclaw/openclaw",
    "run_id": "24939011554",
    "run_url": "https://github.com/openclaw/projectclownfish/actions/runs/24939011554",
    "cluster_id": "ghcrawl-143819-autonomous-smoke",
    "published_at": "2026-04-26T01:36:05.650Z",
    "target": "#70353",
    "action": "close_duplicate",
    "status": "executed",
    "classification": "duplicate",
    "canonical": "#68252",
    "candidate_fix": null,
    "title": null,
    "idempotency_key": "ghcrawl-143819-autonomous-smoke:issue-70353:close_duplicate:canon-68252:2026-04-25T04:04:10Z",
    "reason": "duplicate of the canonical thread",
    "merged_at": null,
    "merge_commit_sha": null,
    "live_state": "closed",
    "live_updated_at": "2026-04-25T04:04:10Z"
  },
  {
    "repo": "openclaw/openclaw",
    "run_id": "24939011554",
    "run_url": "https://github.com/openclaw/projectclownfish/actions/runs/24939011554",
    "cluster_id": "ghcrawl-143819-autonomous-smoke",
    "published_at": "2026-04-26T01:36:05.650Z",
    "target": "#70395",
    "action": "close_duplicate",
    "status": "executed",
    "classification": "duplicate",
    "canonical": "#68252",
    "candidate_fix": null,
    "title": null,
    "idempotency_key": "ghcrawl-143819-autonomous-smoke:issue-70395:close_duplicate:canon-68252:2026-04-23T00:02:25Z",
    "reason": "duplicate of the canonical thread",
    "merged_at": null,
    "merge_commit_sha": null,
    "live_state": "closed",
    "live_updated_at": "2026-04-23T00:02:25Z"
  },
  {
    "repo": "openclaw/openclaw",
    "run_id": "24939011554",
    "run_url": "https://github.com/openclaw/projectclownfish/actions/runs/24939011554",
    "cluster_id": "ghcrawl-143819-autonomous-smoke",
    "published_at": "2026-04-26T01:36:05.650Z",
    "target": "#71133",
    "action": "close_duplicate",
    "status": "executed",
    "classification": "duplicate",
    "canonical": "#68252",
    "candidate_fix": null,
    "title": null,
    "idempotency_key": "ghcrawl-143819-autonomous-smoke:issue-71133:close_duplicate:canon-68252:2026-04-25T06:18:25Z",
    "reason": "duplicate of the canonical thread",
    "merged_at": null,
    "merge_commit_sha": null,
    "live_state": "closed",
    "live_updated_at": "2026-04-25T06:18:25Z"
  },
  {
    "repo": "openclaw/openclaw",
    "run_id": "24943077025",
    "run_url": "https://github.com/openclaw/projectclownfish/actions/runs/24943077025",
    "cluster_id": "ghcrawl-143810-autonomous-smoke",
    "published_at": "2026-04-26T01:36:05.666Z",
    "target": "#41451",
    "action": "close_duplicate",
    "status": "blocked",
    "classification": "duplicate",
    "canonical": "#38797",
    "candidate_fix": null,
    "title": null,
    "idempotency_key": "ghcrawl-143810-autonomous-smoke:#41451:close_duplicate:#38797",
    "reason": "target is not listed in job candidates",
    "merged_at": null,
    "merge_commit_sha": null,
    "live_state": null,
    "live_updated_at": null
  },
  {
    "repo": "openclaw/openclaw",
    "run_id": "24946033542",
    "run_url": "https://github.com/openclaw/projectclownfish/actions/runs/24946033542",
    "cluster_id": "ghcrawl-165995-agentic-merge",
    "published_at": "2026-04-26T02:27:38.431Z",
    "target": "#43556",
    "action": "close_fixed_by_candidate",
    "status": "blocked",
    "classification": "fixed_by_candidate",
    "canonical": "#59390",
    "candidate_fix": "#68397",
    "title": null,
    "idempotency_key": "ghcrawl-165995-agentic-merge-43556-close-fixed-by-candidate-v1",
    "reason": "candidate fix is not listed in job refs",
    "merged_at": null,
    "merge_commit_sha": null,
    "live_state": null,
    "live_updated_at": null
  },
  {
    "repo": "openclaw/openclaw",
    "run_id": "24946033542",
    "run_url": "https://github.com/openclaw/projectclownfish/actions/runs/24946033542",
    "cluster_id": "ghcrawl-165995-agentic-merge",
    "published_at": "2026-04-26T02:27:38.431Z",
    "target": "#56193",
    "action": "close_fixed_by_candidate",
    "status": "blocked",
    "classification": "fixed_by_candidate",
    "canonical": "#59390",
    "candidate_fix": "#68397",
    "title": null,
    "idempotency_key": "ghcrawl-165995-agentic-merge-56193-close-fixed-by-candidate-v1",
    "reason": "candidate fix is not listed in job refs",
    "merged_at": null,
    "merge_commit_sha": null,
    "live_state": null,
    "live_updated_at": null
  },
  {
    "repo": "openclaw/openclaw",
    "run_id": "24946033542",
    "run_url": "https://github.com/openclaw/projectclownfish/actions/runs/24946033542",
    "cluster_id": "ghcrawl-165995-agentic-merge",
    "published_at": "2026-04-26T02:27:38.431Z",
    "target": "#56326",
    "action": "close_fixed_by_candidate",
    "status": "blocked",
    "classification": "fixed_by_candidate",
    "canonical": "#59390",
    "candidate_fix": "#68397",
    "title": null,
    "idempotency_key": "ghcrawl-165995-agentic-merge-56326-close-fixed-by-candidate-v1",
    "reason": "candidate fix is not listed in job refs",
    "merged_at": null,
    "merge_commit_sha": null,
    "live_state": null,
    "live_updated_at": null
  },
  {
    "repo": "openclaw/openclaw",
    "run_id": "24946033542",
    "run_url": "https://github.com/openclaw/projectclownfish/actions/runs/24946033542",
    "cluster_id": "ghcrawl-165995-agentic-merge",
    "published_at": "2026-04-26T02:27:38.431Z",
    "target": "#60965",
    "action": "close_fixed_by_candidate",
    "status": "blocked",
    "classification": "fixed_by_candidate",
    "canonical": "#59390",
    "candidate_fix": "#68397",
    "title": null,
    "idempotency_key": "ghcrawl-165995-agentic-merge-60965-close-fixed-by-candidate-v1",
    "reason": "candidate fix is not listed in job refs",
    "merged_at": null,
    "merge_commit_sha": null,
    "live_state": null,
    "live_updated_at": null
  },
  {
    "repo": "openclaw/openclaw",
    "run_id": "24946033542",
    "run_url": "https://github.com/openclaw/projectclownfish/actions/runs/24946033542",
    "cluster_id": "ghcrawl-165995-agentic-merge",
    "published_at": "2026-04-26T02:27:38.431Z",
    "target": "#61724",
    "action": "close_fixed_by_candidate",
    "status": "blocked",
    "classification": "fixed_by_candidate",
    "canonical": "#59390",
    "candidate_fix": "#68397",
    "title": null,
    "idempotency_key": "ghcrawl-165995-agentic-merge-61724-close-fixed-by-candidate-v1",
    "reason": "candidate fix is not listed in job refs",
    "merged_at": null,
    "merge_commit_sha": null,
    "live_state": null,
    "live_updated_at": null
  },
  {
    "repo": "openclaw/openclaw",
    "run_id": "24946033542",
    "run_url": "https://github.com/openclaw/projectclownfish/actions/runs/24946033542",
    "cluster_id": "ghcrawl-165995-agentic-merge",
    "published_at": "2026-04-26T02:27:38.431Z",
    "target": "#63120",
    "action": "close_fixed_by_candidate",
    "status": "blocked",
    "classification": "fixed_by_candidate",
    "canonical": "#59390",
    "candidate_fix": "#68397",
    "title": null,
    "idempotency_key": "ghcrawl-165995-agentic-merge-63120-close-fixed-by-candidate-v1",
    "reason": "candidate fix is not listed in job refs",
    "merged_at": null,
    "merge_commit_sha": null,
    "live_state": null,
    "live_updated_at": null
  },
  {
    "repo": "openclaw/openclaw",
    "run_id": "24946033542",
    "run_url": "https://github.com/openclaw/projectclownfish/actions/runs/24946033542",
    "cluster_id": "ghcrawl-165995-agentic-merge",
    "published_at": "2026-04-26T02:27:38.431Z",
    "target": "#64714",
    "action": "close_fixed_by_candidate",
    "status": "blocked",
    "classification": "fixed_by_candidate",
    "canonical": "#59390",
    "candidate_fix": "#68397",
    "title": null,
    "idempotency_key": "ghcrawl-165995-agentic-merge-64714-close-fixed-by-candidate-v1",
    "reason": "candidate fix is not listed in job refs",
    "merged_at": null,
    "merge_commit_sha": null,
    "live_state": null,
    "live_updated_at": null
  },
  {
    "repo": "openclaw/openclaw",
    "run_id": "24946033542",
    "run_url": "https://github.com/openclaw/projectclownfish/actions/runs/24946033542",
    "cluster_id": "ghcrawl-165995-agentic-merge",
    "published_at": "2026-04-26T02:27:38.431Z",
    "target": "#67248",
    "action": "close_fixed_by_candidate",
    "status": "blocked",
    "classification": "fixed_by_candidate",
    "canonical": "#59390",
    "candidate_fix": "#68397",
    "title": null,
    "idempotency_key": "ghcrawl-165995-agentic-merge-67248-close-fixed-by-candidate-v1",
    "reason": "candidate fix is not listed in job refs",
    "merged_at": null,
    "merge_commit_sha": null,
    "live_state": null,
    "live_updated_at": null
  },
  {
    "repo": "openclaw/openclaw",
    "run_id": "24946033542",
    "run_url": "https://github.com/openclaw/projectclownfish/actions/runs/24946033542",
    "cluster_id": "ghcrawl-165995-agentic-merge",
    "published_at": "2026-04-26T02:27:38.431Z",
    "target": "#68275",
    "action": "close_fixed_by_candidate",
    "status": "blocked",
    "classification": "fixed_by_candidate",
    "canonical": "#59390",
    "candidate_fix": "#68397",
    "title": null,
    "idempotency_key": "ghcrawl-165995-agentic-merge-68275-close-fixed-by-candidate-v1",
    "reason": "candidate fix is not listed in job refs",
    "merged_at": null,
    "merge_commit_sha": null,
    "live_state": null,
    "live_updated_at": null
  },
  {
    "repo": "openclaw/openclaw",
    "run_id": "24946033542",
    "run_url": "https://github.com/openclaw/projectclownfish/actions/runs/24946033542",
    "cluster_id": "ghcrawl-165995-agentic-merge",
    "published_at": "2026-04-26T02:27:38.431Z",
    "target": "#69166",
    "action": "close_fixed_by_candidate",
    "status": "blocked",
    "classification": "fixed_by_candidate",
    "canonical": "#59390",
    "candidate_fix": "#68397",
    "title": null,
    "idempotency_key": "ghcrawl-165995-agentic-merge-69166-close-fixed-by-candidate-v1",
    "reason": "candidate fix is not listed in job refs",
    "merged_at": null,
    "merge_commit_sha": null,
    "live_state": null,
    "live_updated_at": null
  },
  {
    "repo": "openclaw/openclaw",
    "run_id": "24946036285",
    "run_url": "https://github.com/openclaw/projectclownfish/actions/runs/24946036285",
    "cluster_id": "ghcrawl-165999-agentic-merge",
    "published_at": "2026-04-26T02:20:12.591Z",
    "target": "#56968",
    "action": "close_duplicate",
    "status": "blocked",
    "classification": "duplicate",
    "canonical": "#57256",
    "candidate_fix": "#59685",
    "title": null,
    "idempotency_key": "ghcrawl-165999-agentic-merge:#56968:close_duplicate:#57256:2026-04-04T00:39:03Z",
    "reason": "candidate fix is not listed in job refs",
    "merged_at": null,
    "merge_commit_sha": null,
    "live_state": null,
    "live_updated_at": null
  },
  {
    "repo": "openclaw/openclaw",
    "run_id": "24946036285",
    "run_url": "https://github.com/openclaw/projectclownfish/actions/runs/24946036285",
    "cluster_id": "ghcrawl-165999-agentic-merge",
    "published_at": "2026-04-26T02:20:12.591Z",
    "target": "#60819",
    "action": "close_duplicate",
    "status": "blocked",
    "classification": "duplicate",
    "canonical": "#57256",
    "candidate_fix": "#59685",
    "title": null,
    "idempotency_key": "ghcrawl-165999-agentic-merge:#60819:close_duplicate:#57256:2026-04-04T10:54:46Z",
    "reason": "candidate fix is not listed in job refs",
    "merged_at": null,
    "merge_commit_sha": null,
    "live_state": null,
    "live_updated_at": null
  },
  {
    "repo": "openclaw/openclaw",
    "run_id": "24946036285",
    "run_url": "https://github.com/openclaw/projectclownfish/actions/runs/24946036285",
    "cluster_id": "ghcrawl-165999-agentic-merge",
    "published_at": "2026-04-26T02:20:12.591Z",
    "target": "#64183",
    "action": "close_duplicate",
    "status": "blocked",
    "classification": "duplicate",
    "canonical": "#57256",
    "candidate_fix": "#59685",
    "title": null,
    "idempotency_key": "ghcrawl-165999-agentic-merge:#64183:close_duplicate:#57256:2026-04-10T07:56:52Z",
    "reason": "candidate fix is not listed in job refs",
    "merged_at": null,
    "merge_commit_sha": null,
    "live_state": null,
    "live_updated_at": null
  },
  {
    "repo": "openclaw/openclaw",
    "run_id": "24946558493",
    "run_url": "https://github.com/openclaw/projectclownfish/actions/runs/24946558493",
    "cluster_id": "ghcrawl-165992-agentic-merge",
    "published_at": "2026-04-26T03:04:10.495Z",
    "target": "#41992",
    "action": "close_duplicate",
    "status": "executed",
    "classification": "duplicate",
    "canonical": "#41985",
    "candidate_fix": null,
    "title": null,
    "idempotency_key": "ghcrawl-165992-agentic-merge-41992-close-duplicate-to-41985-v1",
    "reason": "duplicate of the canonical thread",
    "merged_at": null,
    "merge_commit_sha": null,
    "live_state": "closed",
    "live_updated_at": "2026-04-25T06:10:05Z"
  },
  {
    "repo": "openclaw/openclaw",
    "run_id": "24946558493",
    "run_url": "https://github.com/openclaw/projectclownfish/actions/runs/24946558493",
    "cluster_id": "ghcrawl-165992-agentic-merge",
    "published_at": "2026-04-26T03:04:10.495Z",
    "target": "#43242",
    "action": "close_duplicate",
    "status": "executed",
    "classification": "duplicate",
    "canonical": "#41985",
    "candidate_fix": null,
    "title": null,
    "idempotency_key": "ghcrawl-165992-agentic-merge-43242-close-duplicate-to-41985-v1",
    "reason": "duplicate of the canonical thread",
    "merged_at": null,
    "merge_commit_sha": null,
    "live_state": "closed",
    "live_updated_at": "2026-04-25T06:10:01Z"
  },
  {
    "repo": "openclaw/openclaw",
    "run_id": "24946558493",
    "run_url": "https://github.com/openclaw/projectclownfish/actions/runs/24946558493",
    "cluster_id": "ghcrawl-165992-agentic-merge",
    "published_at": "2026-04-26T03:04:10.495Z",
    "target": "#56298",
    "action": "close_duplicate",
    "status": "executed",
    "classification": "duplicate",
    "canonical": "#41985",
    "candidate_fix": null,
    "title": null,
    "idempotency_key": "ghcrawl-165992-agentic-merge-56298-close-duplicate-to-41985-v1",
    "reason": "duplicate of the canonical thread",
    "merged_at": null,
    "merge_commit_sha": null,
    "live_state": "closed",
    "live_updated_at": "2026-04-25T06:09:47Z"
  },
  {
    "repo": "openclaw/openclaw",
    "run_id": "24946558493",
    "run_url": "https://github.com/openclaw/projectclownfish/actions/runs/24946558493",
    "cluster_id": "ghcrawl-165992-agentic-merge",
    "published_at": "2026-04-26T03:04:10.495Z",
    "target": "#63094",
    "action": "close_duplicate",
    "status": "executed",
    "classification": "duplicate",
    "canonical": "#41985",
    "candidate_fix": null,
    "title": null,
    "idempotency_key": "ghcrawl-165992-agentic-merge-63094-close-duplicate-to-41985-v1",
    "reason": "duplicate of the canonical thread",
    "merged_at": null,
    "merge_commit_sha": null,
    "live_state": "closed",
    "live_updated_at": "2026-04-25T06:09:50Z"
  },
  {
    "repo": "openclaw/openclaw",
    "run_id": "24946558493",
    "run_url": "https://github.com/openclaw/projectclownfish/actions/runs/24946558493",
    "cluster_id": "ghcrawl-165992-agentic-merge",
    "published_at": "2026-04-26T03:04:10.495Z",
    "target": "#67622",
    "action": "close_duplicate",
    "status": "executed",
    "classification": "duplicate",
    "canonical": "#41985",
    "candidate_fix": null,
    "title": null,
    "idempotency_key": "ghcrawl-165992-agentic-merge-67622-close-duplicate-to-41985-v1",
    "reason": "duplicate of the canonical thread",
    "merged_at": null,
    "merge_commit_sha": null,
    "live_state": "closed",
    "live_updated_at": "2026-04-25T06:09:43Z"
  },
  {
    "repo": "openclaw/openclaw",
    "run_id": "24946559138",
    "run_url": "https://github.com/openclaw/projectclownfish/actions/runs/24946559138",
    "cluster_id": "ghcrawl-166002-agentic-merge",
    "published_at": "2026-04-26T03:04:54.771Z",
    "target": "#54429",
    "action": "close_duplicate",
    "status": "executed",
    "classification": "duplicate",
    "canonical": "#65184",
    "candidate_fix": null,
    "title": null,
    "idempotency_key": "ghcrawl-166002-agentic-merge:#54429:close_duplicate:#65184:v1",
    "reason": "duplicate of the canonical thread",
    "merged_at": null,
    "merge_commit_sha": null,
    "live_state": "closed",
    "live_updated_at": "2026-03-25T11:08:36Z"
  },
  {
    "repo": "openclaw/openclaw",
    "run_id": "24948420741",
    "run_url": "https://github.com/openclaw/projectclownfish/actions/runs/24948420741",
    "cluster_id": "ghcrawl-165992-agentic-merge",
    "published_at": "2026-04-26T05:01:32.940Z",
    "target": "#30759",
    "action": "close_duplicate",
    "status": "skipped",
    "classification": "duplicate",
    "canonical": "#41985",
    "candidate_fix": null,
    "title": null,
    "idempotency_key": "ghcrawl-165992-agentic-merge-30759-close-duplicate-to-41985-v1",
    "reason": "action status is blocked",
    "merged_at": null,
    "merge_commit_sha": null,
    "live_state": null,
    "live_updated_at": null
  },
  {
    "repo": "openclaw/openclaw",
    "run_id": "24948420741",
    "run_url": "https://github.com/openclaw/projectclownfish/actions/runs/24948420741",
    "cluster_id": "ghcrawl-165992-agentic-merge",
    "published_at": "2026-04-26T05:01:32.940Z",
    "target": "#47933",
    "action": "close_duplicate",
    "status": "skipped",
    "classification": "duplicate",
    "canonical": "#41985",
    "candidate_fix": null,
    "title": null,
    "idempotency_key": "ghcrawl-165992-agentic-merge-47933-close-duplicate-to-41985-v1",
    "reason": "action status is blocked",
    "merged_at": null,
    "merge_commit_sha": null,
    "live_state": null,
    "live_updated_at": null
  },
  {
    "repo": "openclaw/openclaw",
    "run_id": "24948420741",
    "run_url": "https://github.com/openclaw/projectclownfish/actions/runs/24948420741",
    "cluster_id": "ghcrawl-165992-agentic-merge",
    "published_at": "2026-04-26T05:01:32.940Z",
    "target": "#48700",
    "action": "close_duplicate",
    "status": "skipped",
    "classification": "duplicate",
    "canonical": "#41985",
    "candidate_fix": null,
    "title": null,
    "idempotency_key": "ghcrawl-165992-agentic-merge-48700-close-duplicate-to-41985-v1",
    "reason": "action status is blocked",
    "merged_at": null,
    "merge_commit_sha": null,
    "live_state": null,
    "live_updated_at": null
  },
  {
    "repo": "openclaw/openclaw",
    "run_id": "24948420741",
    "run_url": "https://github.com/openclaw/projectclownfish/actions/runs/24948420741",
    "cluster_id": "ghcrawl-165992-agentic-merge",
    "published_at": "2026-04-26T05:01:32.940Z",
    "target": "#69185",
    "action": "close_duplicate",
    "status": "skipped",
    "classification": "duplicate",
    "canonical": "#41985",
    "candidate_fix": null,
    "title": null,
    "idempotency_key": "ghcrawl-165992-agentic-merge-69185-close-duplicate-to-41985-v1",
    "reason": "action status is blocked",
    "merged_at": null,
    "merge_commit_sha": null,
    "live_state": null,
    "live_updated_at": null
  },
  {
    "repo": "openclaw/openclaw",
    "run_id": "24948420741",
    "run_url": "https://github.com/openclaw/projectclownfish/actions/runs/24948420741",
    "cluster_id": "ghcrawl-165992-agentic-merge",
    "published_at": "2026-04-26T05:01:32.940Z",
    "target": "#69447",
    "action": "close_duplicate",
    "status": "skipped",
    "classification": "duplicate",
    "canonical": "#41985",
    "candidate_fix": null,
    "title": null,
    "idempotency_key": "ghcrawl-165992-agentic-merge-69447-close-duplicate-to-41985-v1",
    "reason": "action status is blocked",
    "merged_at": null,
    "merge_commit_sha": null,
    "live_state": null,
    "live_updated_at": null
  },
  {
    "repo": "openclaw/openclaw",
    "run_id": "24952404837",
    "run_url": "https://github.com/openclaw/projectclownfish/actions/runs/24952404837",
    "cluster_id": "ghcrawl-165984-agentic-merge",
    "published_at": "2026-04-26T08:53:39.053Z",
    "target": "#63939",
    "action": "merge_candidate",
    "status": "skipped",
    "classification": "related",
    "canonical": "#53698",
    "candidate_fix": "#63939",
    "title": null,
    "idempotency_key": "ghcrawl-165984:merge_candidate:63939:2026-04-26T083849Z",
    "reason": "action status is blocked",
    "merged_at": null,
    "merge_commit_sha": null,
    "live_state": null,
    "live_updated_at": null
  },
  {
    "repo": "openclaw/openclaw",
    "run_id": "24952404837",
    "run_url": "https://github.com/openclaw/projectclownfish/actions/runs/24952404837",
    "cluster_id": "ghcrawl-165984-agentic-merge",
    "published_at": "2026-04-26T08:53:39.053Z",
    "target": "#71466",
    "action": "merge_candidate",
    "status": "skipped",
    "classification": "related",
    "canonical": "#53698",
    "candidate_fix": "#71466",
    "title": null,
    "idempotency_key": "ghcrawl-165984:merge_candidate:71466:2026-04-26T083849Z",
    "reason": "action status is blocked",
    "merged_at": null,
    "merge_commit_sha": null,
    "live_state": null,
    "live_updated_at": null
  },
  {
    "repo": "openclaw/openclaw",
    "run_id": "24952404837",
    "run_url": "https://github.com/openclaw/projectclownfish/actions/runs/24952404837",
    "cluster_id": "ghcrawl-165984-agentic-merge",
    "published_at": "2026-04-26T08:53:39.053Z",
    "target": "#65215",
    "action": "close_duplicate",
    "status": "skipped",
    "classification": "duplicate",
    "canonical": "#53698",
    "candidate_fix": null,
    "title": null,
    "idempotency_key": "ghcrawl-165984:close_duplicate:65215:2026-04-26T083849Z",
    "reason": "action status is blocked",
    "merged_at": null,
    "merge_commit_sha": null,
    "live_state": null,
    "live_updated_at": null
  },
  {
    "repo": "openclaw/openclaw",
    "run_id": "24952404837",
    "run_url": "https://github.com/openclaw/projectclownfish/actions/runs/24952404837",
    "cluster_id": "ghcrawl-165984-agentic-merge",
    "published_at": "2026-04-26T08:53:39.053Z",
    "target": "#70678",
    "action": "close_duplicate",
    "status": "skipped",
    "classification": "duplicate",
    "canonical": "#53698",
    "candidate_fix": null,
    "title": null,
    "idempotency_key": "ghcrawl-165984:close_duplicate:70678:2026-04-26T083849Z",
    "reason": "action status is blocked",
    "merged_at": null,
    "merge_commit_sha": null,
    "live_state": null,
    "live_updated_at": null
  },
  {
    "repo": "openclaw/openclaw",
    "run_id": "24953939818",
    "run_url": "https://github.com/openclaw/projectclownfish/actions/runs/24953939818",
    "cluster_id": "ghcrawl-165984-agentic-merge",
    "published_at": "2026-04-26T10:07:50.878Z",
    "target": "#53698",
    "action": "close_duplicate",
    "status": "skipped",
    "classification": "duplicate",
    "canonical": "#70678",
    "candidate_fix": "#71466",
    "title": null,
    "idempotency_key": "ghcrawl-165984-agentic-merge:blocked-close-duplicate:53698-to-70678",
    "reason": "action status is blocked",
    "merged_at": null,
    "merge_commit_sha": null,
    "live_state": null,
    "live_updated_at": null
  },
  {
    "repo": "openclaw/openclaw",
    "run_id": "24953939818",
    "run_url": "https://github.com/openclaw/projectclownfish/actions/runs/24953939818",
    "cluster_id": "ghcrawl-165984-agentic-merge",
    "published_at": "2026-04-26T10:07:50.878Z",
    "target": "#65215",
    "action": "close_duplicate",
    "status": "skipped",
    "classification": "duplicate",
    "canonical": "#70678",
    "candidate_fix": "#71466",
    "title": null,
    "idempotency_key": "ghcrawl-165984-agentic-merge:blocked-close-duplicate:65215-to-70678",
    "reason": "action status is blocked",
    "merged_at": null,
    "merge_commit_sha": null,
    "live_state": null,
    "live_updated_at": null
  },
  {
    "repo": "openclaw/openclaw",
    "run_id": "24955178581",
    "run_url": "https://github.com/openclaw/projectclownfish/actions/runs/24955178581",
    "cluster_id": "ghcrawl-165984-agentic-merge",
    "published_at": "2026-04-26T11:14:30.209Z",
    "target": "#71466",
    "action": "merge_candidate",
    "status": "skipped",
    "classification": "canonical",
    "canonical": "#70678",
    "candidate_fix": "#71466",
    "title": null,
    "idempotency_key": "ghcrawl-165984-agentic-merge:merge-candidate-blocked:71466",
    "reason": "action status is blocked",
    "merged_at": null,
    "merge_commit_sha": null,
    "live_state": null,
    "live_updated_at": null
  },
  {
    "repo": "openclaw/openclaw",
    "run_id": "24955178581",
    "run_url": "https://github.com/openclaw/projectclownfish/actions/runs/24955178581",
    "cluster_id": "ghcrawl-165984-agentic-merge",
    "published_at": "2026-04-26T11:14:30.209Z",
    "target": "#53698",
    "action": "close_duplicate",
    "status": "skipped",
    "classification": "duplicate",
    "canonical": "#70678",
    "candidate_fix": "#71466",
    "title": null,
    "idempotency_key": "ghcrawl-165984-agentic-merge:close-duplicate-blocked:53698:70678",
    "reason": "action status is blocked",
    "merged_at": null,
    "merge_commit_sha": null,
    "live_state": null,
    "live_updated_at": null
  },
  {
    "repo": "openclaw/openclaw",
    "run_id": "24955178581",
    "run_url": "https://github.com/openclaw/projectclownfish/actions/runs/24955178581",
    "cluster_id": "ghcrawl-165984-agentic-merge",
    "published_at": "2026-04-26T11:14:30.209Z",
    "target": "#65215",
    "action": "close_duplicate",
    "status": "skipped",
    "classification": "duplicate",
    "canonical": "#70678",
    "candidate_fix": "#71466",
    "title": null,
    "idempotency_key": "ghcrawl-165984-agentic-merge:close-duplicate-blocked:65215:70678",
    "reason": "action status is blocked",
    "merged_at": null,
    "merge_commit_sha": null,
    "live_state": null,
    "live_updated_at": null
  },
  {
    "repo": "openclaw/openclaw",
    "run_id": "24955178581",
    "run_url": "https://github.com/openclaw/projectclownfish/actions/runs/24955178581",
    "cluster_id": "ghcrawl-165984-agentic-merge",
    "published_at": "2026-04-26T11:14:30.209Z",
    "target": "#45474",
    "action": "close_duplicate",
    "status": "skipped",
    "classification": "duplicate",
    "canonical": "#49305",
    "candidate_fix": null,
    "title": null,
    "idempotency_key": "ghcrawl-165984-agentic-merge:close-duplicate-blocked:45474:49305",
    "reason": "action status is blocked",
    "merged_at": null,
    "merge_commit_sha": null,
    "live_state": null,
    "live_updated_at": null
  },
  {
    "repo": "openclaw/openclaw",
    "run_id": "24955904780",
    "run_url": "https://github.com/openclaw/projectclownfish/actions/runs/24955904780",
    "cluster_id": "ghcrawl-165984-agentic-merge",
    "published_at": "2026-04-26T11:56:25.442Z",
    "target": "#71466",
    "action": "close_superseded",
    "status": "skipped",
    "classification": "superseded",
    "canonical": "#70678",
    "candidate_fix": null,
    "title": null,
    "idempotency_key": "ghcrawl-165984-agentic-merge:#71466:close_superseded_after_replacement",
    "reason": "action status is blocked",
    "merged_at": null,
    "merge_commit_sha": null,
    "live_state": null,
    "live_updated_at": null
  },
  {
    "repo": "openclaw/openclaw",
    "run_id": "24955904780",
    "run_url": "https://github.com/openclaw/projectclownfish/actions/runs/24955904780",
    "cluster_id": "ghcrawl-165984-agentic-merge",
    "published_at": "2026-04-26T11:56:25.442Z",
    "target": "#63939",
    "action": "close_superseded",
    "status": "skipped",
    "classification": "superseded",
    "canonical": "#70678",
    "candidate_fix": null,
    "title": null,
    "idempotency_key": "ghcrawl-165984-agentic-merge:#63939:close_superseded_after_replacement",
    "reason": "action status is blocked",
    "merged_at": null,
    "merge_commit_sha": null,
    "live_state": null,
    "live_updated_at": null
  },
  {
    "repo": "openclaw/openclaw",
    "run_id": "24955904780",
    "run_url": "https://github.com/openclaw/projectclownfish/actions/runs/24955904780",
    "cluster_id": "ghcrawl-165984-agentic-merge",
    "published_at": "2026-04-26T11:56:25.442Z",
    "target": "#53698",
    "action": "close_duplicate",
    "status": "skipped",
    "classification": "duplicate",
    "canonical": "#70678",
    "candidate_fix": null,
    "title": null,
    "idempotency_key": "ghcrawl-165984-agentic-merge:#53698:close_duplicate_to_70678",
    "reason": "action status is blocked",
    "merged_at": null,
    "merge_commit_sha": null,
    "live_state": null,
    "live_updated_at": null
  },
  {
    "repo": "openclaw/openclaw",
    "run_id": "24955904780",
    "run_url": "https://github.com/openclaw/projectclownfish/actions/runs/24955904780",
    "cluster_id": "ghcrawl-165984-agentic-merge",
    "published_at": "2026-04-26T11:56:25.442Z",
    "target": "#65215",
    "action": "close_duplicate",
    "status": "skipped",
    "classification": "duplicate",
    "canonical": "#70678",
    "candidate_fix": null,
    "title": null,
    "idempotency_key": "ghcrawl-165984-agentic-merge:#65215:close_duplicate_to_70678",
    "reason": "action status is blocked",
    "merged_at": null,
    "merge_commit_sha": null,
    "live_state": null,
    "live_updated_at": null
  },
  {
    "repo": "openclaw/openclaw",
    "run_id": "24962111806",
    "run_url": "https://github.com/openclaw/projectclownfish/actions/runs/24962111806",
    "cluster_id": "ghcrawl-166014-agentic-merge",
    "published_at": "2026-04-26T17:18:19.703Z",
    "target": "#45718",
    "action": "close_duplicate",
    "status": "skipped",
    "classification": "duplicate",
    "canonical": "#54155",
    "candidate_fix": null,
    "title": null,
    "idempotency_key": "pcw-ghcrawl-166014-close-duplicate-45718-54155",
    "reason": "action status is blocked",
    "merged_at": null,
    "merge_commit_sha": null,
    "live_state": null,
    "live_updated_at": null
  },
  {
    "repo": "openclaw/openclaw",
    "run_id": "24962111806",
    "run_url": "https://github.com/openclaw/projectclownfish/actions/runs/24962111806",
    "cluster_id": "ghcrawl-166014-agentic-merge",
    "published_at": "2026-04-26T17:18:19.703Z",
    "target": "#51977",
    "action": "close_duplicate",
    "status": "skipped",
    "classification": "duplicate",
    "canonical": "#54155",
    "candidate_fix": null,
    "title": null,
    "idempotency_key": "pcw-ghcrawl-166014-close-duplicate-51977-54155",
    "reason": "action status is blocked",
    "merged_at": null,
    "merge_commit_sha": null,
    "live_state": null,
    "live_updated_at": null
  },
  {
    "repo": "openclaw/openclaw",
    "run_id": "24962111806",
    "run_url": "https://github.com/openclaw/projectclownfish/actions/runs/24962111806",
    "cluster_id": "ghcrawl-166014-agentic-merge",
    "published_at": "2026-04-26T17:18:19.703Z",
    "target": "#55334",
    "action": "close_duplicate",
    "status": "skipped",
    "classification": "duplicate",
    "canonical": "#54155",
    "candidate_fix": null,
    "title": null,
    "idempotency_key": "pcw-ghcrawl-166014-close-duplicate-55334-54155",
    "reason": "action status is blocked",
    "merged_at": null,
    "merge_commit_sha": null,
    "live_state": null,
    "live_updated_at": null
  },
  {
    "repo": "openclaw/openclaw",
    "run_id": "24962112832",
    "run_url": "https://github.com/openclaw/projectclownfish/actions/runs/24962112832",
    "cluster_id": "ghcrawl-166000-agentic-merge",
    "published_at": "2026-04-26T17:03:50.322Z",
    "target": "#47935",
    "action": "close_superseded",
    "status": "skipped",
    "classification": "superseded",
    "canonical": "#49430",
    "candidate_fix": "#49430",
    "title": null,
    "idempotency_key": "ghcrawl-166000-agentic-merge:#47935:close_superseded_by_49430_blocked",
    "reason": "action status is blocked",
    "merged_at": null,
    "merge_commit_sha": null,
    "live_state": null,
    "live_updated_at": null
  },
  {
    "repo": "openclaw/openclaw",
    "run_id": "24962112832",
    "run_url": "https://github.com/openclaw/projectclownfish/actions/runs/24962112832",
    "cluster_id": "ghcrawl-166000-agentic-merge",
    "published_at": "2026-04-26T17:03:50.322Z",
    "target": "#56157",
    "action": "close_superseded",
    "status": "skipped",
    "classification": "superseded",
    "canonical": "#49430",
    "candidate_fix": "#49430",
    "title": null,
    "idempotency_key": "ghcrawl-166000-agentic-merge:#56157:close_superseded_by_49430_blocked",
    "reason": "action status is blocked",
    "merged_at": null,
    "merge_commit_sha": null,
    "live_state": null,
    "live_updated_at": null
  },
  {
    "repo": "openclaw/openclaw",
    "run_id": "24962112832",
    "run_url": "https://github.com/openclaw/projectclownfish/actions/runs/24962112832",
    "cluster_id": "ghcrawl-166000-agentic-merge",
    "published_at": "2026-04-26T17:03:50.322Z",
    "target": "#59658",
    "action": "close_superseded",
    "status": "skipped",
    "classification": "superseded",
    "canonical": "#49430",
    "candidate_fix": "#49430",
    "title": null,
    "idempotency_key": "ghcrawl-166000-agentic-merge:#59658:close_superseded_by_49430_blocked",
    "reason": "action status is blocked",
    "merged_at": null,
    "merge_commit_sha": null,
    "live_state": null,
    "live_updated_at": null
  },
  {
    "repo": "openclaw/openclaw",
    "run_id": "24962113785",
    "run_url": "https://github.com/openclaw/projectclownfish/actions/runs/24962113785",
    "cluster_id": "ghcrawl-166006-agentic-merge",
    "published_at": "2026-04-26T17:03:33.538Z",
    "target": "#54381",
    "action": "post_merge_close",
    "status": "blocked",
    "classification": "fixed_by_candidate",
    "canonical": "#62381",
    "candidate_fix": "#62381",
    "title": null,
    "idempotency_key": "ghcrawl-166006-agentic-merge:#54381:post_merge_close:cd89adf0:v1",
    "reason": "target is not listed in job candidates",
    "merged_at": null,
    "merge_commit_sha": null,
    "live_state": null,
    "live_updated_at": null
  },
  {
    "repo": "openclaw/openclaw",
    "run_id": "24962113785",
    "run_url": "https://github.com/openclaw/projectclownfish/actions/runs/24962113785",
    "cluster_id": "ghcrawl-166006-agentic-merge",
    "published_at": "2026-04-26T17:03:33.538Z",
    "target": "#62482",
    "action": "close_superseded",
    "status": "blocked",
    "classification": "superseded",
    "canonical": "#62381",
    "candidate_fix": "#62381",
    "title": null,
    "idempotency_key": "ghcrawl-166006-agentic-merge:#62482:close_superseded:cd89adf0:v1",
    "reason": "close requires ProjectClownfish fix PR opened/pushed or merge executed first",
    "merged_at": null,
    "merge_commit_sha": null,
    "live_state": null,
    "live_updated_at": null
  },
  {
    "repo": "openclaw/openclaw",
    "run_id": "24962783124",
    "run_url": "https://github.com/openclaw/projectclownfish/actions/runs/24962783124",
    "cluster_id": "ghcrawl-166014-agentic-merge",
    "published_at": "2026-04-26T17:44:40.589Z",
    "target": "#45718",
    "action": "close_duplicate",
    "status": "skipped",
    "classification": "duplicate",
    "canonical": "#54155",
    "candidate_fix": null,
    "title": null,
    "idempotency_key": "ghcrawl-166014-agentic-merge:#45718:close_duplicate_blocked_fix_first:2026-04-26",
    "reason": "action status is blocked",
    "merged_at": null,
    "merge_commit_sha": null,
    "live_state": null,
    "live_updated_at": null
  },
  {
    "repo": "openclaw/openclaw",
    "run_id": "24962783124",
    "run_url": "https://github.com/openclaw/projectclownfish/actions/runs/24962783124",
    "cluster_id": "ghcrawl-166014-agentic-merge",
    "published_at": "2026-04-26T17:44:40.589Z",
    "target": "#51977",
    "action": "close_duplicate",
    "status": "skipped",
    "classification": "duplicate",
    "canonical": "#54155",
    "candidate_fix": null,
    "title": null,
    "idempotency_key": "ghcrawl-166014-agentic-merge:#51977:close_duplicate_blocked_fix_first:2026-04-26",
    "reason": "action status is blocked",
    "merged_at": null,
    "merge_commit_sha": null,
    "live_state": null,
    "live_updated_at": null
  },
  {
    "repo": "openclaw/openclaw",
    "run_id": "24962783124",
    "run_url": "https://github.com/openclaw/projectclownfish/actions/runs/24962783124",
    "cluster_id": "ghcrawl-166014-agentic-merge",
    "published_at": "2026-04-26T17:44:40.589Z",
    "target": "#55334",
    "action": "close_duplicate",
    "status": "skipped",
    "classification": "duplicate",
    "canonical": "#54155",
    "candidate_fix": null,
    "title": null,
    "idempotency_key": "ghcrawl-166014-agentic-merge:#55334:close_duplicate_blocked_fix_first:2026-04-26",
    "reason": "action status is blocked",
    "merged_at": null,
    "merge_commit_sha": null,
    "live_state": null,
    "live_updated_at": null
  },
  {
    "repo": "openclaw/openclaw",
    "run_id": "24962937654",
    "run_url": "https://github.com/openclaw/projectclownfish/actions/runs/24962937654",
    "cluster_id": "ghcrawl-165985-agentic-merge",
    "published_at": "2026-04-26T17:52:33.922Z",
    "target": "#65800",
    "action": "close_superseded",
    "status": "skipped",
    "classification": "superseded",
    "canonical": "#71479",
    "candidate_fix": null,
    "title": null,
    "idempotency_key": "ghcrawl-165985-agentic-merge:blocked-close-superseded:#65800:2026-04-13T11:25:23Z",
    "reason": "action status is blocked",
    "merged_at": null,
    "merge_commit_sha": null,
    "live_state": null,
    "live_updated_at": null
  },
  {
    "repo": "openclaw/openclaw",
    "run_id": "24962937654",
    "run_url": "https://github.com/openclaw/projectclownfish/actions/runs/24962937654",
    "cluster_id": "ghcrawl-165985-agentic-merge",
    "published_at": "2026-04-26T17:52:33.922Z",
    "target": "#67063",
    "action": "close_superseded",
    "status": "skipped",
    "classification": "superseded",
    "canonical": "#71479",
    "candidate_fix": null,
    "title": null,
    "idempotency_key": "ghcrawl-165985-agentic-merge:blocked-close-superseded:#67063:2026-04-23T19:33:46Z",
    "reason": "action status is blocked",
    "merged_at": null,
    "merge_commit_sha": null,
    "live_state": null,
    "live_updated_at": null
  },
  {
    "repo": "openclaw/openclaw",
    "run_id": "24962937654",
    "run_url": "https://github.com/openclaw/projectclownfish/actions/runs/24962937654",
    "cluster_id": "ghcrawl-165985-agentic-merge",
    "published_at": "2026-04-26T17:52:33.922Z",
    "target": "#68041",
    "action": "close_superseded",
    "status": "skipped",
    "classification": "superseded",
    "canonical": "#71479",
    "candidate_fix": null,
    "title": null,
    "idempotency_key": "ghcrawl-165985-agentic-merge:blocked-close-superseded:#68041:2026-04-23T19:33:49Z",
    "reason": "action status is blocked",
    "merged_at": null,
    "merge_commit_sha": null,
    "live_state": null,
    "live_updated_at": null
  },
  {
    "repo": "openclaw/openclaw",
    "run_id": "24962937654",
    "run_url": "https://github.com/openclaw/projectclownfish/actions/runs/24962937654",
    "cluster_id": "ghcrawl-165985-agentic-merge",
    "published_at": "2026-04-26T17:52:33.922Z",
    "target": "#70185",
    "action": "close_superseded",
    "status": "skipped",
    "classification": "superseded",
    "canonical": "#71479",
    "candidate_fix": null,
    "title": null,
    "idempotency_key": "ghcrawl-165985-agentic-merge:blocked-close-superseded:#70185:2026-04-24T15:12:21Z",
    "reason": "action status is blocked",
    "merged_at": null,
    "merge_commit_sha": null,
    "live_state": null,
    "live_updated_at": null
  },
  {
    "repo": "openclaw/openclaw",
    "run_id": "24962940666",
    "run_url": "https://github.com/openclaw/projectclownfish/actions/runs/24962940666",
    "cluster_id": "ghcrawl-165995-agentic-merge",
    "published_at": "2026-04-26T17:56:19.583Z",
    "target": "#56326",
    "action": "close_duplicate",
    "status": "skipped",
    "classification": "duplicate",
    "canonical": "#43556",
    "candidate_fix": null,
    "title": null,
    "idempotency_key": "ghcrawl-165995-agentic-merge:#56326:close_duplicate_blocked:2026-03-31T03:12:09Z",
    "reason": "action status is blocked",
    "merged_at": null,
    "merge_commit_sha": null,
    "live_state": null,
    "live_updated_at": null
  },
  {
    "repo": "openclaw/openclaw",
    "run_id": "24962940666",
    "run_url": "https://github.com/openclaw/projectclownfish/actions/runs/24962940666",
    "cluster_id": "ghcrawl-165995-agentic-merge",
    "published_at": "2026-04-26T17:56:19.583Z",
    "target": "#61724",
    "action": "close_duplicate",
    "status": "skipped",
    "classification": "duplicate",
    "canonical": "#43556",
    "candidate_fix": null,
    "title": null,
    "idempotency_key": "ghcrawl-165995-agentic-merge:#61724:close_duplicate_blocked:2026-04-14T13:32:55Z",
    "reason": "action status is blocked",
    "merged_at": null,
    "merge_commit_sha": null,
    "live_state": null,
    "live_updated_at": null
  },
  {
    "repo": "openclaw/openclaw",
    "run_id": "24962940666",
    "run_url": "https://github.com/openclaw/projectclownfish/actions/runs/24962940666",
    "cluster_id": "ghcrawl-165995-agentic-merge",
    "published_at": "2026-04-26T17:56:19.583Z",
    "target": "#63120",
    "action": "close_duplicate",
    "status": "skipped",
    "classification": "duplicate",
    "canonical": "#43556",
    "candidate_fix": null,
    "title": null,
    "idempotency_key": "ghcrawl-165995-agentic-merge:#63120:close_duplicate_blocked:2026-04-08T11:03:33Z",
    "reason": "action status is blocked",
    "merged_at": null,
    "merge_commit_sha": null,
    "live_state": null,
    "live_updated_at": null
  },
  {
    "repo": "openclaw/openclaw",
    "run_id": "24962940666",
    "run_url": "https://github.com/openclaw/projectclownfish/actions/runs/24962940666",
    "cluster_id": "ghcrawl-165995-agentic-merge",
    "published_at": "2026-04-26T17:56:19.583Z",
    "target": "#64714",
    "action": "close_duplicate",
    "status": "skipped",
    "classification": "duplicate",
    "canonical": "#43556",
    "candidate_fix": null,
    "title": null,
    "idempotency_key": "ghcrawl-165995-agentic-merge:#64714:close_duplicate_blocked:2026-04-11T08:26:55Z",
    "reason": "action status is blocked",
    "merged_at": null,
    "merge_commit_sha": null,
    "live_state": null,
    "live_updated_at": null
  },
  {
    "repo": "openclaw/openclaw",
    "run_id": "24962940666",
    "run_url": "https://github.com/openclaw/projectclownfish/actions/runs/24962940666",
    "cluster_id": "ghcrawl-165995-agentic-merge",
    "published_at": "2026-04-26T17:56:19.583Z",
    "target": "#67248",
    "action": "close_duplicate",
    "status": "skipped",
    "classification": "duplicate",
    "canonical": "#43556",
    "candidate_fix": null,
    "title": null,
    "idempotency_key": "ghcrawl-165995-agentic-merge:#67248:close_duplicate_blocked:2026-04-15T15:35:42Z",
    "reason": "action status is blocked",
    "merged_at": null,
    "merge_commit_sha": null,
    "live_state": null,
    "live_updated_at": null
  },
  {
    "repo": "openclaw/openclaw",
    "run_id": "24963241409",
    "run_url": "https://github.com/openclaw/projectclownfish/actions/runs/24963241409",
    "cluster_id": "ghcrawl-166004-agentic-merge",
    "published_at": "2026-04-26T17:58:11.561Z",
    "target": "#41330",
    "action": "post_merge_close",
    "status": "blocked",
    "classification": "fixed_by_candidate",
    "canonical": "#60429",
    "candidate_fix": "#42546",
    "title": null,
    "idempotency_key": "ghcrawl-166004-agentic-merge:#41330:post_merge_close:v1",
    "reason": "candidate fix is not listed in job refs",
    "merged_at": null,
    "merge_commit_sha": null,
    "live_state": null,
    "live_updated_at": null
  },
  {
    "repo": "openclaw/openclaw",
    "run_id": "24963469942",
    "run_url": "https://github.com/openclaw/projectclownfish/actions/runs/24963469942",
    "cluster_id": "ghcrawl-166004-agentic-merge",
    "published_at": "2026-04-26T18:09:35.920Z",
    "target": "#41330",
    "action": "post_merge_close",
    "status": "blocked",
    "classification": "fixed_by_candidate",
    "canonical": "#60429",
    "candidate_fix": "#42546",
    "title": null,
    "idempotency_key": "ghcrawl-166004-agentic-merge:#41330:post_merge_close:2026-04-05T00:02:57Z",
    "reason": "candidate fix is not merged",
    "merged_at": null,
    "merge_commit_sha": null,
    "live_state": null,
    "live_updated_at": null
  },
  {
    "repo": "openclaw/openclaw",
    "run_id": "24964231682",
    "run_url": "https://github.com/openclaw/projectclownfish/actions/runs/24964231682",
    "cluster_id": "ghcrawl-165990-agentic-merge",
    "published_at": "2026-04-26T18:53:30.503Z",
    "target": "#70302",
    "action": "close_superseded",
    "status": "skipped",
    "classification": "superseded",
    "canonical": "#71779",
    "candidate_fix": "#71779",
    "title": null,
    "idempotency_key": "ghcrawl-165990-agentic-merge:#70302:close_superseded:v1",
    "reason": "action status is blocked",
    "merged_at": null,
    "merge_commit_sha": null,
    "live_state": null,
    "live_updated_at": null
  },
  {
    "repo": "openclaw/openclaw",
    "run_id": "24964233962",
    "run_url": "https://github.com/openclaw/projectclownfish/actions/runs/24964233962",
    "cluster_id": "ghcrawl-165996-agentic-merge",
    "published_at": "2026-04-26T18:59:15.386Z",
    "target": "#44118",
    "action": "close_superseded",
    "status": "blocked",
    "classification": "superseded",
    "canonical": "#42228",
    "candidate_fix": "#42228",
    "title": null,
    "idempotency_key": "ghcrawl-165996-agentic-merge:#44118:close_superseded:2026-03-24T20:16:11Z",
    "reason": "close requires ProjectClownfish fix PR opened/pushed or merge executed first",
    "merged_at": null,
    "merge_commit_sha": null,
    "live_state": null,
    "live_updated_at": null
  },
  {
    "repo": "openclaw/openclaw",
    "run_id": "24964233962",
    "run_url": "https://github.com/openclaw/projectclownfish/actions/runs/24964233962",
    "cluster_id": "ghcrawl-165996-agentic-merge",
    "published_at": "2026-04-26T18:59:15.386Z",
    "target": "#67069",
    "action": "close_superseded",
    "status": "blocked",
    "classification": "superseded",
    "canonical": "#67068",
    "candidate_fix": "#67068",
    "title": null,
    "idempotency_key": "ghcrawl-165996-agentic-merge:#67069:close_superseded:2026-04-15T08:22:05Z",
    "reason": "close requires ProjectClownfish fix PR opened/pushed or merge executed first",
    "merged_at": null,
    "merge_commit_sha": null,
    "live_state": null,
    "live_updated_at": null
  },
  {
    "repo": "openclaw/openclaw",
    "run_id": "24964235302",
    "run_url": "https://github.com/openclaw/projectclownfish/actions/runs/24964235302",
    "cluster_id": "ghcrawl-165997-agentic-merge",
    "published_at": "2026-04-26T18:58:11.989Z",
    "target": "#43013",
    "action": "close_superseded",
    "status": "skipped",
    "classification": "superseded",
    "canonical": "#52948",
    "candidate_fix": "#52948",
    "title": null,
    "idempotency_key": "ghcrawl-165997-agentic-merge:#43013:close_superseded_by_52948:2026-03-24T20:16:16Z",
    "reason": "action status is blocked",
    "merged_at": null,
    "merge_commit_sha": null,
    "live_state": null,
    "live_updated_at": null
  },
  {
    "repo": "openclaw/openclaw",
    "run_id": "24964422364",
    "run_url": "https://github.com/openclaw/projectclownfish/actions/runs/24964422364",
    "cluster_id": "ghcrawl-165995-agentic-merge",
    "published_at": "2026-04-26T19:03:46.124Z",
    "target": "#56326",
    "action": "close_duplicate",
    "status": "skipped",
    "classification": "duplicate",
    "canonical": "#43556",
    "candidate_fix": null,
    "title": null,
    "idempotency_key": "ghcrawl-165995-agentic-merge:blocked-close-duplicate:56326:2026-03-31T03:12:09Z",
    "reason": "action status is blocked",
    "merged_at": null,
    "merge_commit_sha": null,
    "live_state": null,
    "live_updated_at": null
  },
  {
    "repo": "openclaw/openclaw",
    "run_id": "24964422364",
    "run_url": "https://github.com/openclaw/projectclownfish/actions/runs/24964422364",
    "cluster_id": "ghcrawl-165995-agentic-merge",
    "published_at": "2026-04-26T19:03:46.124Z",
    "target": "#61724",
    "action": "close_duplicate",
    "status": "skipped",
    "classification": "duplicate",
    "canonical": "#43556",
    "candidate_fix": null,
    "title": null,
    "idempotency_key": "ghcrawl-165995-agentic-merge:blocked-close-duplicate:61724:2026-04-14T13:32:55Z",
    "reason": "action status is blocked",
    "merged_at": null,
    "merge_commit_sha": null,
    "live_state": null,
    "live_updated_at": null
  },
  {
    "repo": "openclaw/openclaw",
    "run_id": "24964422364",
    "run_url": "https://github.com/openclaw/projectclownfish/actions/runs/24964422364",
    "cluster_id": "ghcrawl-165995-agentic-merge",
    "published_at": "2026-04-26T19:03:46.124Z",
    "target": "#63120",
    "action": "close_duplicate",
    "status": "skipped",
    "classification": "duplicate",
    "canonical": "#43556",
    "candidate_fix": null,
    "title": null,
    "idempotency_key": "ghcrawl-165995-agentic-merge:blocked-close-duplicate:63120:2026-04-08T11:03:33Z",
    "reason": "action status is blocked",
    "merged_at": null,
    "merge_commit_sha": null,
    "live_state": null,
    "live_updated_at": null
  },
  {
    "repo": "openclaw/openclaw",
    "run_id": "24964422364",
    "run_url": "https://github.com/openclaw/projectclownfish/actions/runs/24964422364",
    "cluster_id": "ghcrawl-165995-agentic-merge",
    "published_at": "2026-04-26T19:03:46.124Z",
    "target": "#64714",
    "action": "close_duplicate",
    "status": "skipped",
    "classification": "duplicate",
    "canonical": "#43556",
    "candidate_fix": null,
    "title": null,
    "idempotency_key": "ghcrawl-165995-agentic-merge:blocked-close-duplicate:64714:2026-04-11T08:26:55Z",
    "reason": "action status is blocked",
    "merged_at": null,
    "merge_commit_sha": null,
    "live_state": null,
    "live_updated_at": null
  },
  {
    "repo": "openclaw/openclaw",
    "run_id": "24964422364",
    "run_url": "https://github.com/openclaw/projectclownfish/actions/runs/24964422364",
    "cluster_id": "ghcrawl-165995-agentic-merge",
    "published_at": "2026-04-26T19:03:46.124Z",
    "target": "#67248",
    "action": "close_duplicate",
    "status": "skipped",
    "classification": "duplicate",
    "canonical": "#43556",
    "candidate_fix": null,
    "title": null,
    "idempotency_key": "ghcrawl-165995-agentic-merge:blocked-close-duplicate:67248:2026-04-15T15:35:42Z",
    "reason": "action status is blocked",
    "merged_at": null,
    "merge_commit_sha": null,
    "live_state": null,
    "live_updated_at": null
  },
  {
    "repo": "openclaw/openclaw",
    "run_id": "24964423091",
    "run_url": "https://github.com/openclaw/projectclownfish/actions/runs/24964423091",
    "cluster_id": "ghcrawl-165999-agentic-merge",
    "published_at": "2026-04-26T19:24:52.594Z",
    "target": "#56968",
    "action": "close_duplicate",
    "status": "skipped",
    "classification": "duplicate",
    "canonical": "#57256",
    "candidate_fix": "#59685",
    "title": null,
    "idempotency_key": "ghcrawl-165999-agentic-merge:#56968:blocked_duplicate_of_57256:2026-04-04T00:39:03Z",
    "reason": "action status is blocked",
    "merged_at": null,
    "merge_commit_sha": null,
    "live_state": null,
    "live_updated_at": null
  },
  {
    "repo": "openclaw/openclaw",
    "run_id": "24964423091",
    "run_url": "https://github.com/openclaw/projectclownfish/actions/runs/24964423091",
    "cluster_id": "ghcrawl-165999-agentic-merge",
    "published_at": "2026-04-26T19:24:52.594Z",
    "target": "#60819",
    "action": "close_duplicate",
    "status": "skipped",
    "classification": "duplicate",
    "canonical": "#57256",
    "candidate_fix": "#59685",
    "title": null,
    "idempotency_key": "ghcrawl-165999-agentic-merge:#60819:blocked_duplicate_of_57256:2026-04-04T10:54:46Z",
    "reason": "action status is blocked",
    "merged_at": null,
    "merge_commit_sha": null,
    "live_state": null,
    "live_updated_at": null
  },
  {
    "repo": "openclaw/openclaw",
    "run_id": "24966289390",
    "run_url": "https://github.com/openclaw/projectclownfish/actions/runs/24966289390",
    "cluster_id": "ghcrawl-165995-agentic-merge",
    "published_at": "2026-04-26T20:35:11.311Z",
    "target": "#56326",
    "action": "close_duplicate",
    "status": "skipped",
    "classification": "duplicate",
    "canonical": "#43556",
    "candidate_fix": null,
    "title": null,
    "idempotency_key": "pcw-ghcrawl-165995-agentic-merge-56326-close-duplicate-blocked-v1",
    "reason": "action status is blocked",
    "merged_at": null,
    "merge_commit_sha": null,
    "live_state": null,
    "live_updated_at": null
  },
  {
    "repo": "openclaw/openclaw",
    "run_id": "24966289390",
    "run_url": "https://github.com/openclaw/projectclownfish/actions/runs/24966289390",
    "cluster_id": "ghcrawl-165995-agentic-merge",
    "published_at": "2026-04-26T20:35:11.311Z",
    "target": "#61724",
    "action": "close_duplicate",
    "status": "skipped",
    "classification": "duplicate",
    "canonical": "#43556",
    "candidate_fix": null,
    "title": null,
    "idempotency_key": "pcw-ghcrawl-165995-agentic-merge-61724-close-duplicate-blocked-v1",
    "reason": "action status is blocked",
    "merged_at": null,
    "merge_commit_sha": null,
    "live_state": null,
    "live_updated_at": null
  },
  {
    "repo": "openclaw/openclaw",
    "run_id": "24966289390",
    "run_url": "https://github.com/openclaw/projectclownfish/actions/runs/24966289390",
    "cluster_id": "ghcrawl-165995-agentic-merge",
    "published_at": "2026-04-26T20:35:11.311Z",
    "target": "#63120",
    "action": "close_duplicate",
    "status": "skipped",
    "classification": "duplicate",
    "canonical": "#43556",
    "candidate_fix": null,
    "title": null,
    "idempotency_key": "pcw-ghcrawl-165995-agentic-merge-63120-close-duplicate-blocked-v1",
    "reason": "action status is blocked",
    "merged_at": null,
    "merge_commit_sha": null,
    "live_state": null,
    "live_updated_at": null
  },
  {
    "repo": "openclaw/openclaw",
    "run_id": "24966289390",
    "run_url": "https://github.com/openclaw/projectclownfish/actions/runs/24966289390",
    "cluster_id": "ghcrawl-165995-agentic-merge",
    "published_at": "2026-04-26T20:35:11.311Z",
    "target": "#64714",
    "action": "close_duplicate",
    "status": "skipped",
    "classification": "duplicate",
    "canonical": "#43556",
    "candidate_fix": null,
    "title": null,
    "idempotency_key": "pcw-ghcrawl-165995-agentic-merge-64714-close-duplicate-blocked-v1",
    "reason": "action status is blocked",
    "merged_at": null,
    "merge_commit_sha": null,
    "live_state": null,
    "live_updated_at": null
  },
  {
    "repo": "openclaw/openclaw",
    "run_id": "24966289390",
    "run_url": "https://github.com/openclaw/projectclownfish/actions/runs/24966289390",
    "cluster_id": "ghcrawl-165995-agentic-merge",
    "published_at": "2026-04-26T20:35:11.311Z",
    "target": "#67248",
    "action": "close_duplicate",
    "status": "skipped",
    "classification": "duplicate",
    "canonical": "#43556",
    "candidate_fix": null,
    "title": null,
    "idempotency_key": "pcw-ghcrawl-165995-agentic-merge-67248-close-duplicate-blocked-v1",
    "reason": "action status is blocked",
    "merged_at": null,
    "merge_commit_sha": null,
    "live_state": null,
    "live_updated_at": null
  },
  {
    "repo": "openclaw/openclaw",
    "run_id": "24966289390",
    "run_url": "https://github.com/openclaw/projectclownfish/actions/runs/24966289390",
    "cluster_id": "ghcrawl-165995-agentic-merge",
    "published_at": "2026-04-26T20:35:11.311Z",
    "target": "#72331",
    "action": "merge_canonical",
    "status": "blocked",
    "classification": "fix_pr",
    "canonical": null,
    "candidate_fix": null,
    "title": "fix(sessions_spawn): tolerate ACP-only fields for subagent runtime",
    "idempotency_key": null,
    "reason": "merge state status is UNSTABLE",
    "merged_at": null,
    "merge_commit_sha": null,
    "live_state": null,
    "live_updated_at": null
  },
  {
    "repo": "openclaw/openclaw",
    "run_id": "24966557775",
    "run_url": "https://github.com/openclaw/projectclownfish/actions/runs/24966557775",
    "cluster_id": "ghcrawl-165997-agentic-merge",
    "published_at": "2026-04-26T20:50:10.438Z",
    "target": "#72328",
    "action": "merge_canonical",
    "status": "blocked",
    "classification": "fix_pr",
    "canonical": null,
    "candidate_fix": null,
    "title": "fix(ui): stabilize agent model selection on switch",
    "idempotency_key": null,
    "reason": "merge state status is UNSTABLE",
    "merged_at": null,
    "merge_commit_sha": null,
    "live_state": null,
    "live_updated_at": null
  },
  {
    "repo": "openclaw/openclaw",
    "run_id": "24967645047",
    "run_url": "https://github.com/openclaw/projectclownfish/actions/runs/24967645047",
    "cluster_id": "ghcrawl-191452-agentic-merge",
    "published_at": "2026-04-26T21:45:18.750Z",
    "target": "#72375",
    "action": "merge_canonical",
    "status": "executed",
    "classification": "fix_pr",
    "canonical": null,
    "candidate_fix": null,
    "title": "fix: short-circuit live model switch fallback redirects",
    "idempotency_key": null,
    "reason": "merged by ProjectClownfish post-flight",
    "merged_at": "2026-04-26T21:45:03Z",
    "merge_commit_sha": "43a003b8a0629ad2c73947b2a863d99dd506bcb9",
    "live_state": "merged",
    "live_updated_at": null
  },
  {
    "repo": "openclaw/openclaw",
    "run_id": "24967645694",
    "run_url": "https://github.com/openclaw/projectclownfish/actions/runs/24967645694",
    "cluster_id": "ghcrawl-191453-agentic-merge",
    "published_at": "2026-04-26T21:39:30.325Z",
    "target": "#64606",
    "action": "close_fixed_by_candidate",
    "status": "blocked",
    "classification": "fixed_by_candidate",
    "canonical": "#58549",
    "candidate_fix": "#65701",
    "title": null,
    "idempotency_key": "ghcrawl-191453-agentic-merge:#64606:close-fixed-by-65701:2026-04-11T03:11:40Z",
    "reason": "close requires ProjectClownfish fix PR opened/pushed or merge executed first",
    "merged_at": null,
    "merge_commit_sha": null,
    "live_state": null,
    "live_updated_at": null
  },
  {
    "repo": "openclaw/openclaw",
    "run_id": "24967648150",
    "run_url": "https://github.com/openclaw/projectclownfish/actions/runs/24967648150",
    "cluster_id": "ghcrawl-191457-agentic-merge",
    "published_at": "2026-04-26T21:52:47.374Z",
    "target": "#62917",
    "action": "close_fixed_by_candidate",
    "status": "skipped",
    "classification": "fixed_by_candidate",
    "canonical": "#64663",
    "candidate_fix": "#65736",
    "title": null,
    "idempotency_key": "ghcrawl-191457-agentic-merge:#62917:close_fixed_by_candidate:v1",
    "reason": "action status is blocked",
    "merged_at": null,
    "merge_commit_sha": null,
    "live_state": null,
    "live_updated_at": null
  },
  {
    "repo": "openclaw/openclaw",
    "run_id": "24967648150",
    "run_url": "https://github.com/openclaw/projectclownfish/actions/runs/24967648150",
    "cluster_id": "ghcrawl-191457-agentic-merge",
    "published_at": "2026-04-26T21:52:47.374Z",
    "target": "#72377",
    "action": "merge_canonical",
    "status": "blocked",
    "classification": "fix_pr",
    "canonical": null,
    "candidate_fix": null,
    "title": "fix: allow trusted exec approvals home symlinks",
    "idempotency_key": null,
    "reason": "merge state status is UNSTABLE",
    "merged_at": null,
    "merge_commit_sha": null,
    "live_state": null,
    "live_updated_at": null
  },
  {
    "repo": "openclaw/openclaw",
    "run_id": "24967649926",
    "run_url": "https://github.com/openclaw/projectclownfish/actions/runs/24967649926",
    "cluster_id": "ghcrawl-191459-agentic-merge",
    "published_at": "2026-04-26T21:39:03.905Z",
    "target": "#41330",
    "action": "post_merge_close",
    "status": "blocked",
    "classification": "fixed_by_candidate",
    "canonical": "#60429",
    "candidate_fix": "#42546",
    "title": null,
    "idempotency_key": "ghcrawl-191459-agentic-merge:#41330:post_merge_close:2026-04-05T00:02:57Z",
    "reason": "candidate fix is not merged",
    "merged_at": null,
    "merge_commit_sha": null,
    "live_state": null,
    "live_updated_at": null
  },
  {
    "repo": "openclaw/openclaw",
    "run_id": "24967652409",
    "run_url": "https://github.com/openclaw/projectclownfish/actions/runs/24967652409",
    "cluster_id": "ghcrawl-191463-agentic-merge",
    "published_at": "2026-04-26T21:55:01.808Z",
    "target": "#61119",
    "action": "close_superseded",
    "status": "skipped",
    "classification": "superseded",
    "canonical": "#61130",
    "candidate_fix": "#61130",
    "title": null,
    "idempotency_key": "ghcrawl-191463-agentic-merge:#61119:close_superseded_by_61130:2026-04-05T01:28:43Z",
    "reason": "action status is blocked",
    "merged_at": null,
    "merge_commit_sha": null,
    "live_state": null,
    "live_updated_at": null
  },
  {
    "repo": "openclaw/openclaw",
    "run_id": "24967652409",
    "run_url": "https://github.com/openclaw/projectclownfish/actions/runs/24967652409",
    "cluster_id": "ghcrawl-191463-agentic-merge",
    "published_at": "2026-04-26T21:55:01.808Z",
    "target": "#72378",
    "action": "merge_canonical",
    "status": "blocked",
    "classification": "fix_pr",
    "canonical": null,
    "candidate_fix": null,
    "title": "UI: localize command palette labels",
    "idempotency_key": null,
    "reason": "merge state status is UNSTABLE",
    "merged_at": null,
    "merge_commit_sha": null,
    "live_state": null,
    "live_updated_at": null
  },
  {
    "repo": "openclaw/openclaw",
    "run_id": "24968255678",
    "run_url": "https://github.com/openclaw/projectclownfish/actions/runs/24968255678",
    "cluster_id": "ghcrawl-199251-agentic-merge",
    "published_at": "2026-04-26T22:21:31.761Z",
    "target": "#48488",
    "action": "close_fixed_by_candidate",
    "status": "skipped",
    "classification": "fixed_by_candidate",
    "canonical": "#48690",
    "candidate_fix": "#48690",
    "title": null,
    "idempotency_key": "ghcrawl-199251-agentic-merge:#48488:close-fixed-by-candidate:#48690:blocked",
    "reason": "action status is blocked",
    "merged_at": null,
    "merge_commit_sha": null,
    "live_state": null,
    "live_updated_at": null
  },
  {
    "repo": "openclaw/openclaw",
    "run_id": "24968255678",
    "run_url": "https://github.com/openclaw/projectclownfish/actions/runs/24968255678",
    "cluster_id": "ghcrawl-199251-agentic-merge",
    "published_at": "2026-04-26T22:21:31.761Z",
    "target": "#68381",
    "action": "close_superseded",
    "status": "skipped",
    "classification": "superseded",
    "canonical": "#48690",
    "candidate_fix": "#48690",
    "title": null,
    "idempotency_key": "ghcrawl-199251-agentic-merge:#68381:close-superseded-by:#48690:blocked",
    "reason": "action status is blocked",
    "merged_at": null,
    "merge_commit_sha": null,
    "live_state": null,
    "live_updated_at": null
  },
  {
    "repo": "openclaw/openclaw",
    "run_id": "24968256691",
    "run_url": "https://github.com/openclaw/projectclownfish/actions/runs/24968256691",
    "cluster_id": "ghcrawl-199253-agentic-merge",
    "published_at": "2026-04-26T22:11:00.840Z",
    "target": "#52759",
    "action": "close_superseded",
    "status": "skipped",
    "classification": "superseded",
    "canonical": "#34574",
    "candidate_fix": null,
    "title": null,
    "idempotency_key": "ghcrawl-199253-agentic-merge:#52759:close_superseded:v1",
    "reason": "action status is blocked",
    "merged_at": null,
    "merge_commit_sha": null,
    "live_state": null,
    "live_updated_at": null
  },
  {
    "repo": "openclaw/openclaw",
    "run_id": "24968256691",
    "run_url": "https://github.com/openclaw/projectclownfish/actions/runs/24968256691",
    "cluster_id": "ghcrawl-199253-agentic-merge",
    "published_at": "2026-04-26T22:11:00.840Z",
    "target": "#56403",
    "action": "close_superseded",
    "status": "skipped",
    "classification": "superseded",
    "canonical": "#34574",
    "candidate_fix": null,
    "title": null,
    "idempotency_key": "ghcrawl-199253-agentic-merge:#56403:close_superseded:v1",
    "reason": "action status is blocked",
    "merged_at": null,
    "merge_commit_sha": null,
    "live_state": null,
    "live_updated_at": null
  },
  {
    "repo": "openclaw/openclaw",
    "run_id": "24968256691",
    "run_url": "https://github.com/openclaw/projectclownfish/actions/runs/24968256691",
    "cluster_id": "ghcrawl-199253-agentic-merge",
    "published_at": "2026-04-26T22:11:00.840Z",
    "target": "#70877",
    "action": "close_superseded",
    "status": "skipped",
    "classification": "superseded",
    "canonical": "#34574",
    "candidate_fix": null,
    "title": null,
    "idempotency_key": "ghcrawl-199253-agentic-merge:#70877:close_superseded:v1",
    "reason": "action status is blocked",
    "merged_at": null,
    "merge_commit_sha": null,
    "live_state": null,
    "live_updated_at": null
  },
  {
    "repo": "openclaw/openclaw",
    "run_id": "24968261347",
    "run_url": "https://github.com/openclaw/projectclownfish/actions/runs/24968261347",
    "cluster_id": "ghcrawl-199263-agentic-merge",
    "published_at": "2026-04-26T22:23:44.776Z",
    "target": "#41546",
    "action": "close_superseded",
    "status": "skipped",
    "classification": "superseded",
    "canonical": "#41545",
    "candidate_fix": "#42001",
    "title": null,
    "idempotency_key": "ghcrawl-199263-agentic-merge:#41546:close_superseded:2026-04-26T04:37:31Z",
    "reason": "action status is blocked",
    "merged_at": null,
    "merge_commit_sha": null,
    "live_state": null,
    "live_updated_at": null
  },
  {
    "repo": "openclaw/openclaw",
    "run_id": "24968261347",
    "run_url": "https://github.com/openclaw/projectclownfish/actions/runs/24968261347",
    "cluster_id": "ghcrawl-199263-agentic-merge",
    "published_at": "2026-04-26T22:23:44.776Z",
    "target": "#41552",
    "action": "close_superseded",
    "status": "skipped",
    "classification": "superseded",
    "canonical": "#41545",
    "candidate_fix": "#42001",
    "title": null,
    "idempotency_key": "ghcrawl-199263-agentic-merge:#41552:close_superseded:2026-04-26T04:37:35Z",
    "reason": "action status is blocked",
    "merged_at": null,
    "merge_commit_sha": null,
    "live_state": null,
    "live_updated_at": null
  },
  {
    "repo": "openclaw/openclaw",
    "run_id": "24968262940",
    "run_url": "https://github.com/openclaw/projectclownfish/actions/runs/24968262940",
    "cluster_id": "ghcrawl-199267-agentic-merge",
    "published_at": "2026-04-26T22:14:49.340Z",
    "target": "#56516",
    "action": "close_duplicate",
    "status": "skipped",
    "classification": "duplicate",
    "canonical": "#47975",
    "candidate_fix": null,
    "title": null,
    "idempotency_key": "ghcrawl-199267-agentic-merge:#56516:close_duplicate_of_47975:2026-04-26T22-08-18Z",
    "reason": "action status is blocked",
    "merged_at": null,
    "merge_commit_sha": null,
    "live_state": null,
    "live_updated_at": null
  },
  {
    "repo": "openclaw/openclaw",
    "run_id": "24968264891",
    "run_url": "https://github.com/openclaw/projectclownfish/actions/runs/24968264891",
    "cluster_id": "ghcrawl-199270-agentic-merge",
    "published_at": "2026-04-26T22:22:38.841Z",
    "target": "#72389",
    "action": "merge_canonical",
    "status": "blocked",
    "classification": "fix_pr",
    "canonical": null,
    "candidate_fix": null,
    "title": "fix(tui): clear stale streaming after orphaned finals",
    "idempotency_key": null,
    "reason": "merge state status is UNSTABLE",
    "merged_at": null,
    "merge_commit_sha": null,
    "live_state": null,
    "live_updated_at": null
  }
]
