{
  "repo": "openclaw/openclaw",
  "cluster_id": "ghcrawl-165999-agentic-merge",
  "mode": "autonomous",
  "run_id": "24964423091",
  "run_url": "https://github.com/openclaw/projectclownfish/actions/runs/24964423091",
  "head_sha": "3907214d57633ab2c47db83c2266cda41820f960",
  "workflow_conclusion": "success",
  "workflow_status": null,
  "workflow_created_at": null,
  "workflow_updated_at": null,
  "result_status": "planned",
  "source_job": "jobs/openclaw/ghcrawl-165999-agentic-merge.md",
  "published_at": "2026-04-26T19:24:52.594Z",
  "canonical": "https://github.com/openclaw/openclaw/issues/57256",
  "canonical_issue": "https://github.com/openclaw/openclaw/issues/57256",
  "canonical_pr": "https://github.com/openclaw/openclaw/pull/59685",
  "summary": "Classified the hydrated cluster into two ordinary non-security diagnostic subfamilies. Keep #57256 and repair PR #59685 as the status/live-memory-runtime canonical path; keep #44426 as the separate doctor timeout canonical. Do not merge yet: #59685 is useful and editable but lacks a clean current /review and has mergeability unknown. Duplicate closeouts for still-open reports are blocked by require_fix_before_close until the canonical fix path lands.",
  "actions": [
    {
      "target": "#57256",
      "action": "keep_canonical",
      "status": "planned",
      "classification": "canonical",
      "canonical": "#57256",
      "candidate_fix": "#59685",
      "reason": "Best surviving canonical issue for the live gateway memory-runtime false-negative family."
    },
    {
      "target": "#59685",
      "action": "keep_canonical",
      "status": "blocked",
      "classification": "canonical",
      "canonical": "#57256",
      "candidate_fix": "#59685",
      "reason": "Useful editable contributor PR, but not merge-ready under merge policy until refreshed, reviewed, and validated."
    },
    {
      "target": "#44426",
      "action": "keep_canonical",
      "status": "planned",
      "classification": "canonical",
      "canonical": "#44426",
      "candidate_fix": null,
      "reason": "Separate open canonical for transient doctor memory-probe timeout warnings; not safely closable into the status-runtime PR until a fix lands."
    },
    {
      "target": "#56968",
      "action": "close_duplicate",
      "status": "blocked",
      "classification": "duplicate",
      "canonical": "#57256",
      "candidate_fix": "#59685",
      "reason": "Close is blocked on the canonical fix path or fix PR because require_fix_before_close=true."
    },
    {
      "target": "#60819",
      "action": "close_duplicate",
      "status": "blocked",
      "classification": "duplicate",
      "canonical": "#57256",
      "candidate_fix": "#59685",
      "reason": "Close is blocked on the canonical fix path or fix PR because require_fix_before_close=true."
    },
    {
      "target": "#62599",
      "action": "keep_related",
      "status": "planned",
      "classification": "related",
      "canonical": "#57256",
      "candidate_fix": "#59685",
      "reason": "Related status runtime work, but not a high-confidence duplicate closeout because it has unique side-effect and read-only behavior scope."
    },
    {
      "target": "#65066",
      "action": "keep_related",
      "status": "planned",
      "classification": "related",
      "canonical": "#57256",
      "candidate_fix": "#65066",
      "reason": "Related focused PR, not the main canonical path for this cluster and not merge-recommended without current merge preflight."
    },
    {
      "target": "cluster:ghcrawl-165999-agentic-merge",
      "action": "fix_needed",
      "status": "planned",
      "classification": null,
      "canonical": "#57256",
      "candidate_fix": "#59685",
      "reason": "Canonical fix path exists but needs repair/review before merge or post-fix closeout."
    },
    {
      "target": "cluster:ghcrawl-165999-agentic-merge",
      "action": "build_fix_artifact",
      "status": "planned",
      "classification": null,
      "canonical": "#57256",
      "candidate_fix": "#59685",
      "reason": "Fix artifact needed to make the useful contributor PR landable under autonomous policy."
    },
    {
      "target": "#44932",
      "action": "keep_closed",
      "status": "skipped",
      "classification": "duplicate",
      "canonical": "#44426",
      "candidate_fix": null,
      "reason": "Already closed historical context; no closure action allowed."
    },
    {
      "target": "#59894",
      "action": "keep_closed",
      "status": "skipped",
      "classification": "fixed_by_candidate",
      "canonical": "#57256",
      "candidate_fix": null,
      "reason": "Already closed historical context; no closure action allowed."
    },
    {
      "target": "#59942",
      "action": "keep_closed",
      "status": "skipped",
      "classification": "duplicate",
      "canonical": "#60177",
      "candidate_fix": "#65066",
      "reason": "Already closed historical context; no closure action allowed."
    },
    {
      "target": "#60177",
      "action": "keep_closed",
      "status": "skipped",
      "classification": "independent",
      "canonical": "#57256",
      "candidate_fix": "#65066",
      "reason": "Already closed and not actionable in this repository for the external plugin named in the report."
    },
    {
      "target": "#64183",
      "action": "keep_closed",
      "status": "skipped",
      "classification": "duplicate",
      "canonical": "#56968",
      "candidate_fix": "#59685",
      "reason": "Already closed historical context; no closure action allowed."
    },
    {
      "target": "#68171",
      "action": "keep_closed",
      "status": "skipped",
      "classification": "duplicate",
      "canonical": "#44426",
      "candidate_fix": null,
      "reason": "Already closed historical context; no closure action allowed."
    },
    {
      "target": "#46576",
      "action": "keep_closed",
      "status": "skipped",
      "classification": "superseded",
      "canonical": "#44426",
      "candidate_fix": null,
      "reason": "Closed useful historical PR; no direct mutation, but include as source credit for any doctor-timeout repair."
    }
  ],
  "action_counts": {
    "keep_canonical": 3,
    "close_duplicate": 2,
    "keep_related": 2,
    "fix_needed": 1,
    "build_fix_artifact": 1,
    "keep_closed": 7
  },
  "action_status_counts": {
    "planned": 6,
    "blocked": 3,
    "skipped": 7
  },
  "apply_counts": {
    "skipped": 2
  },
  "needs_human": [],
  "apply_actions": [
    {
      "target": "#56968",
      "action": "close_duplicate",
      "status": "skipped",
      "classification": "duplicate",
      "canonical": "#57256",
      "candidate_fix": "#59685",
      "title": null,
      "idempotency_key": "ghcrawl-165999-agentic-merge:#56968:blocked_duplicate_of_57256:2026-04-04T00:39:03Z",
      "reason": "action status is blocked",
      "merged_at": null,
      "merge_commit_sha": null,
      "live_state": null,
      "live_updated_at": null
    },
    {
      "target": "#60819",
      "action": "close_duplicate",
      "status": "skipped",
      "classification": "duplicate",
      "canonical": "#57256",
      "candidate_fix": "#59685",
      "title": null,
      "idempotency_key": "ghcrawl-165999-agentic-merge:#60819:blocked_duplicate_of_57256:2026-04-04T10:54:46Z",
      "reason": "action status is blocked",
      "merged_at": null,
      "merge_commit_sha": null,
      "live_state": null,
      "live_updated_at": null
    }
  ]
}
